{
  "project_info": {
    "project_number": "1005345375717",
    "project_id": "comfy-learn",
    "storage_bucket": "comfy-learn.firebasestorage.app"
  },
  "client": [
    {
      "client_info": {
        "mobilesdk_app_id": "1:1005345375717:android:56efdf8bf8dbc6bba35b0c",
        "android_client_info": {
          "package_name": "com.hompimpa.comfylearn"
        }
      },
      "oauth_client": [
        {
          "client_id": "1005345375717-bn28hfduke2t1qkph6ccsf903uaef7lo.apps.googleusercontent.com",
          "client_type": 1,
          "android_info": {
            "package_name": "com.hompimpa.comfylearn",
            "certificate_hash": "c0531fd2c70a9d363c88db0f3b7aceef98741848"
          }
        },
        {
          "client_id": "1005345375717-rrb8pub4u2ucbn7j99kinrnf8lmlbc03.apps.googleusercontent.com",
          "client_type": 1,
          "android_info": {
            "package_name": "com.hompimpa.comfylearn",
            "certificate_hash": "fe7fa33aa4cf23bc604736162b966ef559fb24d3"
          }
        },
        {
          "client_id": "1005345375717-p602uvi1pps108dpnjbfiuhrum66n1an.apps.googleusercontent.com",
          "client_type": 3
        }
      ],
      "api_key": [
        {
          "current_key": "AIzaSyAyNvLzjKENM7Myi4NDzeKf8ry91UA-9rA"
        }
      ],
      "services": {
        "appinvite_service": {
          "other_platform_oauth_client": [
            {
              "client_id": "1005345375717-5o338i0p524vpnqnb776mg33o55q5mfo.apps.googleusercontent.com",
              "client_type": 3
            }
          ]
        }
      }
    }
  ],
  "configuration_version": "1"
}